config/__init__.py
config/asgi.py
config/settings.py
config/urls.py
config/wsgi.py
django_package_boilerplate/__init__.py
django_package_boilerplate/admin.py
django_package_boilerplate/apps.py
django_package_boilerplate/gateway.py
django_package_boilerplate/models.py
django_package_boilerplate/pagination.py
django_package_boilerplate/serializers.py
django_package_boilerplate/settings.py
django_package_boilerplate/tests.py
django_package_boilerplate/urls.py
django_package_boilerplate/views.py
django_package_boilerplate/migrations/__init__.py
django_package_boilerplate-0.1.3.dist-info/LICENSE
django_package_boilerplate-0.1.3.dist-info/METADATA
django_package_boilerplate-0.1.3.dist-info/WHEEL
django_package_boilerplate-0.1.3.dist-info/top_level.txt
django_package_boilerplate-0.1.3.dist-info/RECORD
