Metadata-Version: 2.1
Name: django-package-boilerplate
Version: 0.1.3
Summary: A boilerplate Django app package for easy integration
Home-page: https://github.com/RUNNERS-IM/django-package-boilerplate
Author: Runners Co., Ltd.
Author-email: dev@runners.im
License: UNKNOWN
Platform: UNKNOWN
Classifier: Framework :: Django
Classifier: Programming Language :: Python :: 3
Classifier: License :: OSI Approved :: MIT License
Classifier: Operating System :: OS Independent
Requires-Python: >=3.6
Requires-Dist: django >=3.0
Requires-Dist: requests
